[
  {
    "티커": "GOOGL",
    "종목명": "Alphabet Inc.",
    "날짜": "2026-01-30",
    "시가": 334.32,
    "고가": 339.95,
    "저가": 332.29,
    "종가": 338.0,
    "거래량": 30131351,
    "MA5": 336.01,
    "MA10": 331.89,
    "MA20": 328.87
  },
  {
    "티커": "GOOGL",
    "종목명": "Alphabet Inc.",
    "날짜": "2026-01-29",
    "시가": 340.3,
    "고가": 342.29,
    "저가": 326.54,
    "종가": 338.25,
    "거래량": 39785600,
    "MA5": 334.0,
    "MA10": 331.37,
    "MA20": 327.62
  },
  {
    "티커": "GOOGL",
    "종목명": "Alphabet Inc.",
    "날짜": "2026-01-28",
    "시가": 336.06,
    "고가": 337.54,
    "저가": 331.94,
    "종가": 336.01,
    "거래량": 27434400,
    "MA5": 332.46,
    "MA10": 331.13,
    "MA20": null
  },
  {
    "티커": "GOOGL",
    "종목명": "Alphabet Inc.",
    "날짜": "2026-01-27",
    "시가": 335.37,
    "고가": 337.91,
    "저가": 333.48,
    "종가": 334.55,
    "거래량": 21636200,
    "MA5": 330.93,
    "MA10": 331.12,
    "MA20": null
  },
  {
    "티커": "GOOGL",
    "종목명": "Alphabet Inc.",
    "날짜": "2026-01-26",
    "시가": 327.81,
    "고가": 335.84,
    "저가": 327.0,
    "종가": 333.26,
    "거래량": 26042100,
    "MA5": 328.42,
    "MA10": 330.86,
    "MA20": null
  },
  {
    "티커": "GOOGL",
    "종목명": "Alphabet Inc.",
    "날짜": "2026-01-23",
    "시가": 332.49,
    "고가": 333.69,
    "저가": 327.45,
    "종가": 327.93,
    "거래량": 27280000,
    "MA5": 327.77,
    "MA10": 330.39,
    "MA20": null
  },
  {
    "티커": "GOOGL",
    "종목명": "Alphabet Inc.",
    "날짜": "2026-01-22",
    "시가": 334.45,
    "고가": 335.15,
    "저가": 328.75,
    "종가": 330.54,
    "거래량": 26253600,
    "MA5": 328.74,
    "MA10": 330.14,
    "MA20": null
  },
  {
    "티커": "GOOGL",
    "종목명": "Alphabet Inc.",
    "날짜": "2026-01-21",
    "시가": 320.92,
    "고가": 332.48,
    "저가": 319.35,
    "종가": 328.38,
    "거래량": 35386600,
    "MA5": 329.8,
    "MA10": 329.28,
    "MA20": null
  },
  {
    "티커": "GOOGL",
    "종목명": "Alphabet Inc.",
    "날짜": "2026-01-20",
    "시가": 320.87,
    "고가": 327.73,
    "저가": 320.43,
    "종가": 322.0,
    "거래량": 35361000,
    "MA5": 331.32,
    "MA10": 327.88,
    "MA20": null
  },
  {
    "티커": "GOOGL",
    "종목명": "Alphabet Inc.",
    "날짜": "2026-01-16",
    "시가": 334.41,
    "고가": 334.65,
    "저가": 327.7,
    "종가": 330.0,
    "거래량": 40341600,
    "MA5": 333.29,
    "MA10": 327.33,
    "MA20": null
  },
  {
    "티커": "GOOGL",
    "종목명": "Alphabet Inc.",
    "날짜": "2026-01-15",
    "시가": 337.65,
    "고가": 337.69,
    "저가": 330.74,
    "종가": 332.78,
    "거래량": 28442400,
    "MA5": 333.0,
    "MA10": 325.85,
    "MA20": null
  },
  {
    "티커": "GOOGL",
    "종목명": "Alphabet Inc.",
    "날짜": "2026-01-14",
    "시가": 335.06,
    "고가": 336.52,
    "저가": 330.48,
    "종가": 335.84,
    "거래량": 28525600,
    "MA5": 331.54,
    "MA10": 323.87,
    "MA20": null
  },
  {
    "티커": "GOOGL",
    "종목명": "Alphabet Inc.",
    "날짜": "2026-01-13",
    "시가": 334.95,
    "고가": 340.49,
    "저가": 333.62,
    "종가": 335.97,
    "거래량": 33517600,
    "MA5": 328.76,
    "MA10": null,
    "MA20": null
  },
  {
    "티커": "GOOGL",
    "종목명": "Alphabet Inc.",
    "날짜": "2026-01-12",
    "시가": 325.8,
    "고가": 334.04,
    "저가": 325.0,
    "종가": 331.86,
    "거래량": 33923900,
    "MA5": 324.44,
    "MA10": null,
    "MA20": null
  },
  {
    "티커": "GOOGL",
    "종목명": "Alphabet Inc.",
    "날짜": "2026-01-09",
    "시가": 327.09,
    "고가": 330.83,
    "저가": 325.8,
    "종가": 328.57,
    "거래량": 26214200,
    "MA5": 321.37,
    "MA10": null,
    "MA20": null
  },
  {
    "티커": "GOOGL",
    "종목명": "Alphabet Inc.",
    "날짜": "2026-01-08",
    "시가": 328.97,
    "고가": 330.32,
    "저가": 321.5,
    "종가": 325.44,
    "거래량": 31896100,
    "MA5": 318.69,
    "MA10": null,
    "MA20": null
  },
  {
    "티커": "GOOGL",
    "종목명": "Alphabet Inc.",
    "날짜": "2026-01-07",
    "시가": 314.36,
    "고가": 326.15,
    "저가": 314.19,
    "종가": 321.98,
    "거래량": 35104400,
    "MA5": 316.2,
    "MA10": null,
    "MA20": null
  },
  {
    "티커": "GOOGL",
    "종목명": "Alphabet Inc.",
    "날짜": "2026-01-06",
    "시가": 316.4,
    "고가": 320.94,
    "저가": 311.78,
    "종가": 314.34,
    "거래량": 31212100,
    "MA5": null,
    "MA10": null,
    "MA20": null
  },
  {
    "티커": "GOOGL",
    "종목명": "Alphabet Inc.",
    "날짜": "2026-01-05",
    "시가": 317.66,
    "고가": 319.02,
    "저가": 314.63,
    "종가": 316.54,
    "거래량": 30195600,
    "MA5": null,
    "MA10": null,
    "MA20": null
  },
  {
    "티커": "GOOGL",
    "종목명": "Alphabet Inc.",
    "날짜": "2026-01-02",
    "시가": 316.9,
    "고가": 322.5,
    "저가": 310.33,
    "종가": 315.15,
    "거래량": 32009400,
    "MA5": null,
    "MA10": null,
    "MA20": null
  }
]